pwnstar/__init__.py
pwnstar/gateways.py
pwnstar/proxy.py
pwnstar/pwnstar.py
pwnstar/targets.py
pwnstar/tubes/__init__.py
pwnstar/tubes/gateway.py
pwnstar/tubes/process.py
pwnstar/tubes/remote.py
pwnstar/tubes/utils.py
pwnstar/ws_static/index.html
pwnstar/ws_static/css/bootstrap.css
pwnstar/ws_static/css/main.css
pwnstar/ws_static/css/xterm.css
pwnstar/ws_static/img/redo-solid.svg
pwnstar/ws_static/js/bootstrap.js
pwnstar/ws_static/js/jquery.js
pwnstar/ws_static/js/main.js
pwnstar/ws_static/js/xterm.js
pwnstar-0.3.11.dist-info/METADATA
pwnstar-0.3.11.dist-info/WHEEL
pwnstar-0.3.11.dist-info/entry_points.txt
pwnstar-0.3.11.dist-info/top_level.txt
pwnstar-0.3.11.dist-info/RECORD
