Metadata-Version: 2.1
Name: pwnstar
Version: 0.3.11
Summary: UNKNOWN
Home-page: UNKNOWN
License: UNKNOWN
Platform: UNKNOWN
Requires-Python: >=3.7
Requires-Dist: aiohttp
